locallibs
