Metadata-Version: 1.2
Name: locallibs
Version: 0.1.1.dev1
Summary: Local Library Management Tool
Home-page: https://github.com/SabujXi/locallibs
Author: Md. Sabuj Sarker
Author-email: md.sabuj.sarker@gmail.com
License: UNKNOWN
Platform: UNKNOWN
Requires-Python: >=2.7
